{
  "Andaman and Nicobar Islands": {
    "Arrested": 144,
    "Convicted": 32,
    "Externee": 37,
    "Deportee": 79,
    "UIFP": 150,
    "Suspect": 57,
    "total": 499
  },
  "Andhra Pradesh": {
    "Arrested": 99,
    "Convicted": 40,
    "Externee": 11,
    "Deportee": 169,
    "UIFP": 73,
    "Suspect": 53,
    "total": 445
  },
  "Arunachal Pradesh": {
    "Arrested": 45,
    "Convicted": 29,
    "Externee": 78,
    "Deportee": 164,
    "UIFP": 71,
    "Suspect": 193,
    "total": 580
  },
  "Assam": {
    "Arrested": 22,
    "Convicted": 30,
    "Externee": 161,
    "Deportee": 161,
    "UIFP": 29,
    "Suspect": 191,
    "total": 594
  },
  "Bihar": {
    "Arrested": 135,
    "Convicted": 140,
    "Externee": 52,
    "Deportee": 37,
    "UIFP": 115,
    "Suspect": 88,
    "total": 567
  },
  "Chandigarh": {
    "Arrested": 16,
    "Convicted": 79,
    "Externee": 173,
    "Deportee": 35,
    "UIFP": 137,
    "Suspect": 10,
    "total": 450
  },
  "Chhattisgarh": {
    "Arrested": 146,
    "Convicted": 162,
    "Externee": 35,
    "Deportee": 94,
    "UIFP": 183,
    "Suspect": 119,
    "total": 739
  },
  "DD & DNH": {
    "Arrested": 36,
    "Convicted": 127,
    "Externee": 181,
    "Deportee": 102,
    "UIFP": 111,
    "Suspect": 67,
    "total": 624
  },
  "Delhi": {
    "Arrested": 63,
    "Convicted": 84,
    "Externee": 68,
    "Deportee": 154,
    "UIFP": 198,
    "Suspect": 95,
    "total": 662
  },
  "Goa": {
    "Arrested": 56,
    "Convicted": 24,
    "Externee": 143,
    "Deportee": 172,
    "UIFP": 195,
    "Suspect": 171,
    "total": 761
  },
  "Gujarat": {
    "Arrested": 158,
    "Convicted": 22,
    "Externee": 100,
    "Deportee": 133,
    "UIFP": 71,
    "Suspect": 87,
    "total": 571
  },
  "Haryana": {
    "Arrested": 191,
    "Convicted": 134,
    "Externee": 19,
    "Deportee": 60,
    "UIFP": 24,
    "Suspect": 137,
    "total": 565
  },
  "Himachal Pradesh": {
    "Arrested": 78,
    "Convicted": 43,
    "Externee": 120,
    "Deportee": 18,
    "UIFP": 135,
    "Suspect": 198,
    "total": 592
  },
  "Jammu Kashmir & Ladakh": {
    "Arrested": 32,
    "Convicted": 114,
    "Externee": 138,
    "Deportee": 41,
    "UIFP": 186,
    "Suspect": 177,
    "total": 688
  },
  "Jharkhand": {
    "Arrested": 131,
    "Convicted": 65,
    "Externee": 129,
    "Deportee": 181,
    "UIFP": 57,
    "Suspect": 42,
    "total": 605
  },
  "Karnataka": {
    "Arrested": 41,
    "Convicted": 14,
    "Externee": 39,
    "Deportee": 83,
    "UIFP": 57,
    "Suspect": 44,
    "total": 278
  },
  "Kerala": {
    "Arrested": 187,
    "Convicted": 180,
    "Externee": 165,
    "Deportee": 190,
    "UIFP": 62,
    "Suspect": 161,
    "total": 945
  },
  "Lakshadweep": {
    "Arrested": 101,
    "Convicted": 99,
    "Externee": 171,
    "Deportee": 38,
    "UIFP": 56,
    "Suspect": 139,
    "total": 604
  },
  "Madhya Pradesh": {
    "Arrested": 38,
    "Convicted": 169,
    "Externee": 157,
    "Deportee": 188,
    "UIFP": 47,
    "Suspect": 174,
    "total": 773
  },
  "Maharashtra": {
    "Arrested": 105,
    "Convicted": 127,
    "Externee": 77,
    "Deportee": 160,
    "UIFP": 192,
    "Suspect": 91,
    "total": 752
  },
  "Manipur": {
    "Arrested": 166,
    "Convicted": 23,
    "Externee": 123,
    "Deportee": 106,
    "UIFP": 28,
    "Suspect": 50,
    "total": 496
  },
  "Meghalaya": {
    "Arrested": 161,
    "Convicted": 37,
    "Externee": 184,
    "Deportee": 186,
    "UIFP": 77,
    "Suspect": 79,
    "total": 724
  },
  "Mizoram": {
    "Arrested": 169,
    "Convicted": 66,
    "Externee": 86,
    "Deportee": 192,
    "UIFP": 120,
    "Suspect": 21,
    "total": 654
  },
  "Nagaland": {
    "Arrested": 12,
    "Convicted": 39,
    "Externee": 40,
    "Deportee": 119,
    "UIFP": 59,
    "Suspect": 113,
    "total": 382
  },
  "Odisha": {
    "Arrested": 96,
    "Convicted": 35,
    "Externee": 12,
    "Deportee": 27,
    "UIFP": 86,
    "Suspect": 49,
    "total": 305
  },
  "Puducherry": {
    "Arrested": 176,
    "Convicted": 92,
    "Externee": 114,
    "Deportee": 66,
    "UIFP": 135,
    "Suspect": 181,
    "total": 764
  },
  "Punjab": {
    "Arrested": 131,
    "Convicted": 163,
    "Externee": 198,
    "Deportee": 135,
    "UIFP": 46,
    "Suspect": 120,
    "total": 793
  },
  "Rajasthan": {
    "Arrested": 71,
    "Convicted": 61,
    "Externee": 154,
    "Deportee": 178,
    "UIFP": 126,
    "Suspect": 153,
    "total": 743
  },
  "Sikkim": {
    "Arrested": 49,
    "Convicted": 29,
    "Externee": 194,
    "Deportee": 36,
    "UIFP": 79,
    "Suspect": 58,
    "total": 445
  },
  "Tamil Nadu": {
    "Arrested": 43,
    "Convicted": 126,
    "Externee": 139,
    "Deportee": 88,
    "UIFP": 118,
    "Suspect": 192,
    "total": 706
  },
  "Telangana": {
    "Arrested": 29,
    "Convicted": 19,
    "Externee": 154,
    "Deportee": 70,
    "UIFP": 72,
    "Suspect": 85,
    "total": 429
  },
  "Tripura": {
    "Arrested": 113,
    "Convicted": 42,
    "Externee": 101,
    "Deportee": 82,
    "UIFP": 129,
    "Suspect": 131,
    "total": 598
  },
  "Uttar Pradesh": {
    "Arrested": 193,
    "Convicted": 22,
    "Externee": 37,
    "Deportee": 173,
    "UIFP": 38,
    "Suspect": 42,
    "total": 505
  },
  "Uttarakhand": {
    "Arrested": 44,
    "Convicted": 177,
    "Externee": 192,
    "Deportee": 162,
    "UIFP": 142,
    "Suspect": 177,
    "total": 894
  },
  "West Bengal": {
    "Arrested": 28,
    "Convicted": 142,
    "Externee": 66,
    "Deportee": 27,
    "UIFP": 86,
    "Suspect": 189,
    "total": 538
  },
  "CFPB": {
    "Arrested": 78,
    "Convicted": 88,
    "Externee": 195,
    "Deportee": 73,
    "UIFP": 146,
    "Suspect": 48,
    "total": 628
  }
}