{
  "Andaman and Nicobar Islands": {
    "tp_tp": {
      "hit": 71,
      "no_hit": 108,
      "total": 179,
      "inter_state": 31,
      "own_state": 40
    }
  },
  "Andhra Pradesh": {
    "tp_tp": {
      "hit": 53,
      "no_hit": 28,
      "total": 81,
      "inter_state": 12,
      "own_state": 41
    }
  },
  "Arunachal Pradesh": {
    "tp_tp": {
      "hit": 176,
      "no_hit": 117,
      "total": 293,
      "inter_state": 152,
      "own_state": 24
    }
  },
  "Assam": {
    "tp_tp": {
      "hit": 256,
      "no_hit": 76,
      "total": 332,
      "inter_state": 116,
      "own_state": 140
    }
  },
  "Bihar": {
    "tp_tp": {
      "hit": 271,
      "no_hit": 64,
      "total": 335,
      "inter_state": 183,
      "own_state": 88
    }
  },
  "Chandigarh": {
    "tp_tp": {
      "hit": 71,
      "no_hit": 100,
      "total": 171,
      "inter_state": 2,
      "own_state": 69
    }
  },
  "Chhattisgarh": {
    "tp_tp": {
      "hit": 66,
      "no_hit": 53,
      "total": 119,
      "inter_state": 5,
      "own_state": 61
    }
  },
  "Dadra and Nagar Haveli and Daman and Diu": {
    "tp_tp": {
      "hit": 186,
      "no_hit": 141,
      "total": 327,
      "inter_state": 142,
      "own_state": 44
    }
  },
  "Delhi": {
    "tp_tp": {
      "hit": 183,
      "no_hit": 24,
      "total": 207,
      "inter_state": 121,
      "own_state": 62
    }
  },
  "Goa": {
    "tp_tp": {
      "hit": 208,
      "no_hit": 100,
      "total": 308,
      "inter_state": 59,
      "own_state": 149
    }
  },
  "Gujarat": {
    "tp_tp": {
      "hit": 201,
      "no_hit": 70,
      "total": 271,
      "inter_state": 83,
      "own_state": 118
    }
  },
  "Haryana": {
    "tp_tp": {
      "hit": 203,
      "no_hit": 45,
      "total": 248,
      "inter_state": 5,
      "own_state": 198
    }
  },
  "Himachal Pradesh": {
    "tp_tp": {
      "hit": 127,
      "no_hit": 137,
      "total": 264,
      "inter_state": 21,
      "own_state": 106
    }
  },
  "Jammu Kashmir & Ladakh": {
    "tp_tp": {
      "hit": 81,
      "no_hit": 134,
      "total": 215,
      "inter_state": 61,
      "own_state": 20
    }
  },
  "Jharkhand": {
    "tp_tp": {
      "hit": 243,
      "no_hit": 112,
      "total": 355,
      "inter_state": 37,
      "own_state": 206
    }
  },
  "Karnataka": {
    "tp_tp": {
      "hit": 262,
      "no_hit": 31,
      "total": 293,
      "inter_state": 53,
      "own_state": 209
    }
  },
  "Kerala": {
    "tp_tp": {
      "hit": 64,
      "no_hit": 149,
      "total": 213,
      "inter_state": 37,
      "own_state": 27
    }
  },
  "Lakshadweep": {
    "tp_tp": {
      "hit": 158,
      "no_hit": 48,
      "total": 206,
      "inter_state": 26,
      "own_state": 132
    }
  },
  "Madhya Pradesh": {
    "tp_tp": {
      "hit": 290,
      "no_hit": 47,
      "total": 337,
      "inter_state": 121,
      "own_state": 169
    }
  },
  "Maharashtra": {
    "tp_tp": {
      "hit": 255,
      "no_hit": 130,
      "total": 385,
      "inter_state": 168,
      "own_state": 87
    }
  },
  "Manipur": {
    "tp_tp": {
      "hit": 72,
      "no_hit": 135,
      "total": 207,
      "inter_state": 48,
      "own_state": 24
    }
  },
  "Meghalaya": {
    "tp_tp": {
      "hit": 274,
      "no_hit": 35,
      "total": 309,
      "inter_state": 157,
      "own_state": 117
    }
  },
  "Mizoram": {
    "tp_tp": {
      "hit": 133,
      "no_hit": 27,
      "total": 160,
      "inter_state": 40,
      "own_state": 93
    }
  },
  "Nagaland": {
    "tp_tp": {
      "hit": 54,
      "no_hit": 85,
      "total": 139,
      "inter_state": 29,
      "own_state": 25
    }
  },
  "Odisha": {
    "tp_tp": {
      "hit": 84,
      "no_hit": 104,
      "total": 188,
      "inter_state": 53,
      "own_state": 31
    }
  },
  "Puducherry": {
    "tp_tp": {
      "hit": 76,
      "no_hit": 22,
      "total": 98,
      "inter_state": 47,
      "own_state": 29
    }
  },
  "Punjab": {
    "tp_tp": {
      "hit": 153,
      "no_hit": 93,
      "total": 246,
      "inter_state": 51,
      "own_state": 102
    }
  },
  "Rajasthan": {
    "tp_tp": {
      "hit": 179,
      "no_hit": 120,
      "total": 299,
      "inter_state": 42,
      "own_state": 137
    }
  },
  "Sikkim": {
    "tp_tp": {
      "hit": 68,
      "no_hit": 52,
      "total": 120,
      "inter_state": 9,
      "own_state": 59
    }
  },
  "Tamil Nadu": {
    "tp_tp": {
      "hit": 100,
      "no_hit": 134,
      "total": 234,
      "inter_state": 13,
      "own_state": 87
    }
  },
  "Telangana": {
    "tp_tp": {
      "hit": 50,
      "no_hit": 47,
      "total": 97,
      "inter_state": 30,
      "own_state": 20
    }
  },
  "Tripura": {
    "tp_tp": {
      "hit": 240,
      "no_hit": 111,
      "total": 351,
      "inter_state": 26,
      "own_state": 214
    }
  },
  "Uttar Pradesh": {
    "tp_tp": {
      "hit": 213,
      "no_hit": 106,
      "total": 319,
      "inter_state": 116,
      "own_state": 97
    }
  },
  "Uttarakhand": {
    "tp_tp": {
      "hit": 53,
      "no_hit": 67,
      "total": 120,
      "inter_state": 13,
      "own_state": 40
    }
  },
  "West Bengal": {
    "tp_tp": {
      "hit": 98,
      "no_hit": 142,
      "total": 240,
      "inter_state": 30,
      "own_state": 68
    }
  }
}