{
  "Andaman and Nicobar Islands": {
    "Arrested": 48,
    "Convicted": 142,
    "Externee": 75,
    "Deportee": 61,
    "UIFP": 46,
    "Suspect": 51,
    "UDB": 120,
    "Absconder": 23,
    "total": 566
  },
  "Andhra Pradesh": {
    "Arrested": 71,
    "Convicted": 45,
    "Externee": 153,
    "Deportee": 42,
    "UIFP": 13,
    "Suspect": 175,
    "UDB": 155,
    "Absconder": 189,
    "total": 843
  },
  "Arunachal Pradesh": {
    "Arrested": 153,
    "Convicted": 43,
    "Externee": 63,
    "Deportee": 65,
    "UIFP": 66,
    "Suspect": 25,
    "UDB": 152,
    "Absconder": 44,
    "total": 611
  },
  "Assam": {
    "Arrested": 89,
    "Convicted": 115,
    "Externee": 81,
    "Deportee": 126,
    "UIFP": 89,
    "Suspect": 50,
    "UDB": 43,
    "Absconder": 153,
    "total": 746
  },
  "Bihar": {
    "Arrested": 165,
    "Convicted": 178,
    "Externee": 56,
    "Deportee": 21,
    "UIFP": 126,
    "Suspect": 138,
    "UDB": 179,
    "Absconder": 86,
    "total": 949
  },
  "Chandigarh": {
    "Arrested": 51,
    "Convicted": 95,
    "Externee": 124,
    "Deportee": 177,
    "UIFP": 75,
    "Suspect": 79,
    "UDB": 105,
    "Absconder": 62,
    "total": 768
  },
  "Chhattisgarh": {
    "Arrested": 86,
    "Convicted": 113,
    "Externee": 177,
    "Deportee": 60,
    "UIFP": 100,
    "Suspect": 69,
    "UDB": 118,
    "Absconder": 47,
    "total": 770
  },
  "Dadra and Nagar Haveli and Daman and Diu": {
    "Arrested": 129,
    "Convicted": 126,
    "Externee": 31,
    "Deportee": 200,
    "UIFP": 113,
    "Suspect": 44,
    "UDB": 94,
    "Absconder": 138,
    "total": 875
  },
  "Delhi": {
    "Arrested": 182,
    "Convicted": 66,
    "Externee": 94,
    "Deportee": 35,
    "UIFP": 147,
    "Suspect": 119,
    "UDB": 190,
    "Absconder": 160,
    "total": 993
  },
  "Goa": {
    "Arrested": 97,
    "Convicted": 138,
    "Externee": 187,
    "Deportee": 142,
    "UIFP": 103,
    "Suspect": 32,
    "UDB": 122,
    "Absconder": 80,
    "total": 901
  },
  "Gujarat": {
    "Arrested": 81,
    "Convicted": 158,
    "Externee": 80,
    "Deportee": 14,
    "UIFP": 50,
    "Suspect": 64,
    "UDB": 130,
    "Absconder": 130,
    "total": 707
  },
  "Haryana": {
    "Arrested": 89,
    "Convicted": 88,
    "Externee": 85,
    "Deportee": 96,
    "UIFP": 106,
    "Suspect": 31,
    "UDB": 138,
    "Absconder": 190,
    "total": 823
  },
  "Himachal Pradesh": {
    "Arrested": 72,
    "Convicted": 155,
    "Externee": 178,
    "Deportee": 16,
    "UIFP": 22,
    "Suspect": 21,
    "UDB": 107,
    "Absconder": 72,
    "total": 643
  },
  "Jammu Kashmir & Ladakh": {
    "Arrested": 103,
    "Convicted": 183,
    "Externee": 89,
    "Deportee": 134,
    "UIFP": 159,
    "Suspect": 154,
    "UDB": 68,
    "Absconder": 48,
    "total": 938
  },
  "Jharkhand": {
    "Arrested": 139,
    "Convicted": 141,
    "Externee": 119,
    "Deportee": 191,
    "UIFP": 161,
    "Suspect": 76,
    "UDB": 173,
    "Absconder": 100,
    "total": 1100
  },
  "Karnataka": {
    "Arrested": 14,
    "Convicted": 120,
    "Externee": 36,
    "Deportee": 187,
    "UIFP": 118,
    "Suspect": 25,
    "UDB": 10,
    "Absconder": 106,
    "total": 616
  },
  "Kerala": {
    "Arrested": 154,
    "Convicted": 108,
    "Externee": 199,
    "Deportee": 157,
    "UIFP": 73,
    "Suspect": 95,
    "UDB": 51,
    "Absconder": 43,
    "total": 880
  },
  "Lakshadweep": {
    "Arrested": 67,
    "Convicted": 15,
    "Externee": 78,
    "Deportee": 169,
    "UIFP": 98,
    "Suspect": 46,
    "UDB": 86,
    "Absconder": 125,
    "total": 684
  },
  "Madhya Pradesh": {
    "Arrested": 49,
    "Convicted": 93,
    "Externee": 12,
    "Deportee": 120,
    "UIFP": 91,
    "Suspect": 157,
    "UDB": 81,
    "Absconder": 50,
    "total": 653
  },
  "Maharashtra": {
    "Arrested": 188,
    "Convicted": 31,
    "Externee": 41,
    "Deportee": 48,
    "UIFP": 123,
    "Suspect": 95,
    "UDB": 189,
    "Absconder": 95,
    "total": 810
  },
  "Manipur": {
    "Arrested": 193,
    "Convicted": 21,
    "Externee": 73,
    "Deportee": 143,
    "UIFP": 99,
    "Suspect": 18,
    "UDB": 131,
    "Absconder": 168,
    "total": 846
  },
  "Meghalaya": {
    "Arrested": 108,
    "Convicted": 186,
    "Externee": 144,
    "Deportee": 173,
    "UIFP": 141,
    "Suspect": 101,
    "UDB": 57,
    "Absconder": 157,
    "total": 1067
  },
  "Mizoram": {
    "Arrested": 108,
    "Convicted": 76,
    "Externee": 189,
    "Deportee": 105,
    "UIFP": 66,
    "Suspect": 142,
    "UDB": 64,
    "Absconder": 31,
    "total": 781
  },
  "Nagaland": {
    "Arrested": 93,
    "Convicted": 169,
    "Externee": 194,
    "Deportee": 155,
    "UIFP": 23,
    "Suspect": 144,
    "UDB": 39,
    "Absconder": 41,
    "total": 858
  },
  "Odisha": {
    "Arrested": 125,
    "Convicted": 59,
    "Externee": 34,
    "Deportee": 112,
    "UIFP": 10,
    "Suspect": 60,
    "UDB": 63,
    "Absconder": 10,
    "total": 473
  },
  "Puducherry": {
    "Arrested": 121,
    "Convicted": 115,
    "Externee": 14,
    "Deportee": 74,
    "UIFP": 110,
    "Suspect": 97,
    "UDB": 89,
    "Absconder": 25,
    "total": 645
  },
  "Punjab": {
    "Arrested": 151,
    "Convicted": 123,
    "Externee": 119,
    "Deportee": 183,
    "UIFP": 57,
    "Suspect": 113,
    "UDB": 154,
    "Absconder": 48,
    "total": 948
  },
  "Rajasthan": {
    "Arrested": 63,
    "Convicted": 139,
    "Externee": 149,
    "Deportee": 115,
    "UIFP": 191,
    "Suspect": 72,
    "UDB": 38,
    "Absconder": 186,
    "total": 953
  },
  "Sikkim": {
    "Arrested": 164,
    "Convicted": 50,
    "Externee": 36,
    "Deportee": 78,
    "UIFP": 10,
    "Suspect": 114,
    "UDB": 128,
    "Absconder": 135,
    "total": 715
  },
  "Tamil Nadu": {
    "Arrested": 129,
    "Convicted": 115,
    "Externee": 171,
    "Deportee": 164,
    "UIFP": 174,
    "Suspect": 134,
    "UDB": 108,
    "Absconder": 150,
    "total": 1145
  },
  "Telangana": {
    "Arrested": 40,
    "Convicted": 103,
    "Externee": 83,
    "Deportee": 62,
    "UIFP": 150,
    "Suspect": 62,
    "UDB": 164,
    "Absconder": 184,
    "total": 848
  },
  "Tripura": {
    "Arrested": 148,
    "Convicted": 124,
    "Externee": 51,
    "Deportee": 112,
    "UIFP": 123,
    "Suspect": 78,
    "UDB": 165,
    "Absconder": 123,
    "total": 924
  },
  "Uttar Pradesh": {
    "Arrested": 90,
    "Convicted": 139,
    "Externee": 80,
    "Deportee": 30,
    "UIFP": 68,
    "Suspect": 48,
    "UDB": 52,
    "Absconder": 24,
    "total": 531
  },
  "Uttarakhand": {
    "Arrested": 168,
    "Convicted": 70,
    "Externee": 177,
    "Deportee": 44,
    "UIFP": 49,
    "Suspect": 101,
    "UDB": 29,
    "Absconder": 35,
    "total": 673
  },
  "West Bengal": {
    "Arrested": 122,
    "Convicted": 33,
    "Externee": 25,
    "Deportee": 151,
    "UIFP": 126,
    "Suspect": 57,
    "UDB": 130,
    "Absconder": 146,
    "total": 790
  }
}