{
  "Andaman and Nicobar Islands": {
    "tp": {
      "enrollment": 114,
      "hit": 95,
      "nohit": 11,
      "total": 106
    },
    "cp": {
      "enrollment": 460,
      "hit": 263,
      "nohit": 38,
      "total": 301
    },
    "mesa": {
      "enrollment": 309,
      "hit": 95,
      "nohit": 83,
      "total": 178
    }
  },
  "Andhra Pradesh": {
    "tp": {
      "enrollment": 438,
      "hit": 391,
      "nohit": 13,
      "total": 404
    },
    "cp": {
      "enrollment": 332,
      "hit": 165,
      "nohit": 9,
      "total": 174
    },
    "mesa": {
      "enrollment": 278,
      "hit": 165,
      "nohit": 25,
      "total": 190
    }
  },
  "Arunachal Pradesh": {
    "tp": {
      "enrollment": 206,
      "hit": 102,
      "nohit": 67,
      "total": 169
    },
    "cp": {
      "enrollment": 452,
      "hit": 394,
      "nohit": 23,
      "total": 417
    },
    "mesa": {
      "enrollment": 205,
      "hit": 122,
      "nohit": 32,
      "total": 154
    }
  },
  "Assam": {
    "tp": {
      "enrollment": 385,
      "hit": 186,
      "nohit": 89,
      "total": 275
    },
    "cp": {
      "enrollment": 151,
      "hit": 106,
      "nohit": 41,
      "total": 147
    },
    "mesa": {
      "enrollment": 280,
      "hit": 52,
      "nohit": 176,
      "total": 228
    }
  },
  "Bihar": {
    "tp": {
      "enrollment": 274,
      "hit": 244,
      "nohit": 9,
      "total": 253
    },
    "cp": {
      "enrollment": 210,
      "hit": 119,
      "nohit": 34,
      "total": 153
    },
    "mesa": {
      "enrollment": 431,
      "hit": 348,
      "nohit": 14,
      "total": 362
    }
  },
  "Chandigarh": {
    "tp": {
      "enrollment": 409,
      "hit": 78,
      "nohit": 278,
      "total": 356
    },
    "cp": {
      "enrollment": 142,
      "hit": 94,
      "nohit": 12,
      "total": 106
    },
    "mesa": {
      "enrollment": 456,
      "hit": 298,
      "nohit": 42,
      "total": 340
    }
  },
  "Chhattisgarh": {
    "tp": {
      "enrollment": 468,
      "hit": 256,
      "nohit": 142,
      "total": 398
    },
    "cp": {
      "enrollment": 390,
      "hit": 267,
      "nohit": 15,
      "total": 282
    },
    "mesa": {
      "enrollment": 176,
      "hit": 122,
      "nohit": 3,
      "total": 125
    }
  },
  "Dadra and Nagar Haveli and Daman and Diu": {
    "tp": {
      "enrollment": 241,
      "hit": 51,
      "nohit": 58,
      "total": 109
    },
    "cp": {
      "enrollment": 231,
      "hit": 150,
      "nohit": 59,
      "total": 209
    },
    "mesa": {
      "enrollment": 475,
      "hit": 435,
      "nohit": 32,
      "total": 467
    }
  },
  "Delhi": {
    "tp": {
      "enrollment": 424,
      "hit": 360,
      "nohit": 2,
      "total": 362
    },
    "cp": {
      "enrollment": 105,
      "hit": 103,
      "nohit": 1,
      "total": 104
    },
    "mesa": {
      "enrollment": 336,
      "hit": 253,
      "nohit": 79,
      "total": 332
    }
  },
  "Goa": {
    "tp": {
      "enrollment": 326,
      "hit": 179,
      "nohit": 66,
      "total": 245
    },
    "cp": {
      "enrollment": 106,
      "hit": 84,
      "nohit": 10,
      "total": 94
    },
    "mesa": {
      "enrollment": 122,
      "hit": 64,
      "nohit": 12,
      "total": 76
    }
  },
  "Gujarat": {
    "tp": {
      "enrollment": 129,
      "hit": 72,
      "nohit": 18,
      "total": 90
    },
    "cp": {
      "enrollment": 272,
      "hit": 138,
      "nohit": 121,
      "total": 259
    },
    "mesa": {
      "enrollment": 342,
      "hit": 341,
      "nohit": 1,
      "total": 342
    }
  },
  "Haryana": {
    "tp": {
      "enrollment": 367,
      "hit": 148,
      "nohit": 120,
      "total": 268
    },
    "cp": {
      "enrollment": 453,
      "hit": 159,
      "nohit": 279,
      "total": 438
    },
    "mesa": {
      "enrollment": 473,
      "hit": 225,
      "nohit": 186,
      "total": 411
    }
  },
  "Himachal Pradesh": {
    "tp": {
      "enrollment": 378,
      "hit": 101,
      "nohit": 79,
      "total": 180
    },
    "cp": {
      "enrollment": 414,
      "hit": 314,
      "nohit": 20,
      "total": 334
    },
    "mesa": {
      "enrollment": 167,
      "hit": 156,
      "nohit": 4,
      "total": 160
    }
  },
  "Jammu Kashmir & Ladakh": {
    "tp": {
      "enrollment": 214,
      "hit": 110,
      "nohit": 47,
      "total": 157
    },
    "cp": {
      "enrollment": 191,
      "hit": 80,
      "nohit": 4,
      "total": 84
    },
    "mesa": {
      "enrollment": 289,
      "hit": 280,
      "nohit": 9,
      "total": 289
    }
  },
  "Jharkhand": {
    "tp": {
      "enrollment": 446,
      "hit": 402,
      "nohit": 28,
      "total": 430
    },
    "cp": {
      "enrollment": 152,
      "hit": 102,
      "nohit": 10,
      "total": 112
    },
    "mesa": {
      "enrollment": 252,
      "hit": 208,
      "nohit": 22,
      "total": 230
    }
  },
  "Karnataka": {
    "tp": {
      "enrollment": 390,
      "hit": 344,
      "nohit": 38,
      "total": 382
    },
    "cp": {
      "enrollment": 144,
      "hit": 102,
      "nohit": 27,
      "total": 129
    },
    "mesa": {
      "enrollment": 154,
      "hit": 75,
      "nohit": 25,
      "total": 100
    }
  },
  "Kerala": {
    "tp": {
      "enrollment": 165,
      "hit": 124,
      "nohit": 16,
      "total": 140
    },
    "cp": {
      "enrollment": 499,
      "hit": 262,
      "nohit": 156,
      "total": 418
    },
    "mesa": {
      "enrollment": 160,
      "hit": 159,
      "nohit": 0,
      "total": 159
    }
  },
  "Lakshadweep": {
    "tp": {
      "enrollment": 468,
      "hit": 244,
      "nohit": 119,
      "total": 363
    },
    "cp": {
      "enrollment": 179,
      "hit": 176,
      "nohit": 0,
      "total": 176
    },
    "mesa": {
      "enrollment": 402,
      "hit": 307,
      "nohit": 37,
      "total": 344
    }
  },
  "Madhya Pradesh": {
    "tp": {
      "enrollment": 191,
      "hit": 58,
      "nohit": 6,
      "total": 64
    },
    "cp": {
      "enrollment": 246,
      "hit": 241,
      "nohit": 5,
      "total": 246
    },
    "mesa": {
      "enrollment": 293,
      "hit": 64,
      "nohit": 47,
      "total": 111
    }
  },
  "Maharashtra": {
    "tp": {
      "enrollment": 457,
      "hit": 197,
      "nohit": 209,
      "total": 406
    },
    "cp": {
      "enrollment": 500,
      "hit": 331,
      "nohit": 153,
      "total": 484
    },
    "mesa": {
      "enrollment": 228,
      "hit": 221,
      "nohit": 4,
      "total": 225
    }
  },
  "Manipur": {
    "tp": {
      "enrollment": 479,
      "hit": 243,
      "nohit": 19,
      "total": 262
    },
    "cp": {
      "enrollment": 453,
      "hit": 253,
      "nohit": 193,
      "total": 446
    },
    "mesa": {
      "enrollment": 460,
      "hit": 188,
      "nohit": 194,
      "total": 382
    }
  },
  "Meghalaya": {
    "tp": {
      "enrollment": 238,
      "hit": 117,
      "nohit": 111,
      "total": 228
    },
    "cp": {
      "enrollment": 337,
      "hit": 266,
      "nohit": 48,
      "total": 314
    },
    "mesa": {
      "enrollment": 306,
      "hit": 67,
      "nohit": 65,
      "total": 132
    }
  },
  "Mizoram": {
    "tp": {
      "enrollment": 143,
      "hit": 76,
      "nohit": 61,
      "total": 137
    },
    "cp": {
      "enrollment": 126,
      "hit": 88,
      "nohit": 25,
      "total": 113
    },
    "mesa": {
      "enrollment": 428,
      "hit": 350,
      "nohit": 67,
      "total": 417
    }
  },
  "Nagaland": {
    "tp": {
      "enrollment": 148,
      "hit": 96,
      "nohit": 37,
      "total": 133
    },
    "cp": {
      "enrollment": 143,
      "hit": 118,
      "nohit": 24,
      "total": 142
    },
    "mesa": {
      "enrollment": 131,
      "hit": 88,
      "nohit": 29,
      "total": 117
    }
  },
  "Odisha": {
    "tp": {
      "enrollment": 368,
      "hit": 262,
      "nohit": 74,
      "total": 336
    },
    "cp": {
      "enrollment": 394,
      "hit": 380,
      "nohit": 9,
      "total": 389
    },
    "mesa": {
      "enrollment": 445,
      "hit": 50,
      "nohit": 265,
      "total": 315
    }
  },
  "Puducherry": {
    "tp": {
      "enrollment": 435,
      "hit": 165,
      "nohit": 87,
      "total": 252
    },
    "cp": {
      "enrollment": 430,
      "hit": 315,
      "nohit": 19,
      "total": 334
    },
    "mesa": {
      "enrollment": 321,
      "hit": 285,
      "nohit": 9,
      "total": 294
    }
  },
  "Punjab": {
    "tp": {
      "enrollment": 487,
      "hit": 143,
      "nohit": 264,
      "total": 407
    },
    "cp": {
      "enrollment": 118,
      "hit": 102,
      "nohit": 4,
      "total": 106
    },
    "mesa": {
      "enrollment": 264,
      "hit": 144,
      "nohit": 86,
      "total": 230
    }
  },
  "Rajasthan": {
    "tp": {
      "enrollment": 301,
      "hit": 204,
      "nohit": 49,
      "total": 253
    },
    "cp": {
      "enrollment": 243,
      "hit": 120,
      "nohit": 117,
      "total": 237
    },
    "mesa": {
      "enrollment": 145,
      "hit": 124,
      "nohit": 7,
      "total": 131
    }
  },
  "Sikkim": {
    "tp": {
      "enrollment": 183,
      "hit": 98,
      "nohit": 53,
      "total": 151
    },
    "cp": {
      "enrollment": 270,
      "hit": 216,
      "nohit": 14,
      "total": 230
    },
    "mesa": {
      "enrollment": 470,
      "hit": 366,
      "nohit": 44,
      "total": 410
    }
  },
  "Tamil Nadu": {
    "tp": {
      "enrollment": 360,
      "hit": 210,
      "nohit": 105,
      "total": 315
    },
    "cp": {
      "enrollment": 480,
      "hit": 72,
      "nohit": 362,
      "total": 434
    },
    "mesa": {
      "enrollment": 415,
      "hit": 183,
      "nohit": 118,
      "total": 301
    }
  },
  "Telangana": {
    "tp": {
      "enrollment": 124,
      "hit": 50,
      "nohit": 59,
      "total": 109
    },
    "cp": {
      "enrollment": 230,
      "hit": 105,
      "nohit": 12,
      "total": 117
    },
    "mesa": {
      "enrollment": 355,
      "hit": 255,
      "nohit": 47,
      "total": 302
    }
  },
  "Tripura": {
    "tp": {
      "enrollment": 150,
      "hit": 58,
      "nohit": 34,
      "total": 92
    },
    "cp": {
      "enrollment": 304,
      "hit": 133,
      "nohit": 121,
      "total": 254
    },
    "mesa": {
      "enrollment": 233,
      "hit": 159,
      "nohit": 66,
      "total": 225
    }
  },
  "Uttar Pradesh": {
    "tp": {
      "enrollment": 420,
      "hit": 397,
      "nohit": 13,
      "total": 410
    },
    "cp": {
      "enrollment": 282,
      "hit": 239,
      "nohit": 36,
      "total": 275
    },
    "mesa": {
      "enrollment": 355,
      "hit": 225,
      "nohit": 51,
      "total": 276
    }
  },
  "Uttarakhand": {
    "tp": {
      "enrollment": 137,
      "hit": 118,
      "nohit": 5,
      "total": 123
    },
    "cp": {
      "enrollment": 104,
      "hit": 93,
      "nohit": 8,
      "total": 101
    },
    "mesa": {
      "enrollment": 365,
      "hit": 54,
      "nohit": 284,
      "total": 338
    }
  },
  "West Bengal": {
    "tp": {
      "enrollment": 321,
      "hit": 239,
      "nohit": 22,
      "total": 261
    },
    "cp": {
      "enrollment": 419,
      "hit": 101,
      "nohit": 288,
      "total": 389
    },
    "mesa": {
      "enrollment": 388,
      "hit": 382,
      "nohit": 0,
      "total": 382
    }
  }
}