{
  "Andaman and Nicobar Islands": {
    "Arrested": 172,
    "Convicted": 11,
    "Externee": 44,
    "Deportee": 16,
    "UIFP": 106,
    "Suspect": 146,
    "UDB": 153,
    "Absconder": 178,
    "total": 826
  },
  "Andhra Pradesh": {
    "Arrested": 55,
    "Convicted": 74,
    "Externee": 32,
    "Deportee": 160,
    "UIFP": 60,
    "Suspect": 169,
    "UDB": 162,
    "Absconder": 145,
    "total": 857
  },
  "Arunachal Pradesh": {
    "Arrested": 26,
    "Convicted": 87,
    "Externee": 68,
    "Deportee": 29,
    "UIFP": 184,
    "Suspect": 175,
    "UDB": 85,
    "Absconder": 180,
    "total": 834
  },
  "Assam": {
    "Arrested": 90,
    "Convicted": 197,
    "Externee": 153,
    "Deportee": 143,
    "UIFP": 57,
    "Suspect": 102,
    "UDB": 184,
    "Absconder": 133,
    "total": 1059
  },
  "Bihar": {
    "Arrested": 14,
    "Convicted": 40,
    "Externee": 134,
    "Deportee": 169,
    "UIFP": 111,
    "Suspect": 11,
    "UDB": 16,
    "Absconder": 40,
    "total": 535
  },
  "Chandigarh": {
    "Arrested": 84,
    "Convicted": 58,
    "Externee": 103,
    "Deportee": 169,
    "UIFP": 176,
    "Suspect": 189,
    "UDB": 100,
    "Absconder": 47,
    "total": 926
  },
  "Chhattisgarh": {
    "Arrested": 152,
    "Convicted": 82,
    "Externee": 72,
    "Deportee": 11,
    "UIFP": 88,
    "Suspect": 140,
    "UDB": 53,
    "Absconder": 17,
    "total": 615
  },
  "Dadra and Nagar Haveli and Daman and Diu": {
    "Arrested": 121,
    "Convicted": 29,
    "Externee": 86,
    "Deportee": 114,
    "UIFP": 168,
    "Suspect": 79,
    "UDB": 47,
    "Absconder": 170,
    "total": 814
  },
  "Delhi": {
    "Arrested": 75,
    "Convicted": 192,
    "Externee": 156,
    "Deportee": 78,
    "UIFP": 28,
    "Suspect": 127,
    "UDB": 25,
    "Absconder": 100,
    "total": 781
  },
  "Goa": {
    "Arrested": 86,
    "Convicted": 12,
    "Externee": 154,
    "Deportee": 27,
    "UIFP": 61,
    "Suspect": 156,
    "UDB": 99,
    "Absconder": 41,
    "total": 636
  },
  "Gujarat": {
    "Arrested": 123,
    "Convicted": 155,
    "Externee": 198,
    "Deportee": 63,
    "UIFP": 131,
    "Suspect": 163,
    "UDB": 68,
    "Absconder": 66,
    "total": 967
  },
  "Haryana": {
    "Arrested": 107,
    "Convicted": 72,
    "Externee": 154,
    "Deportee": 60,
    "UIFP": 132,
    "Suspect": 63,
    "UDB": 61,
    "Absconder": 41,
    "total": 690
  },
  "Himachal Pradesh": {
    "Arrested": 183,
    "Convicted": 186,
    "Externee": 20,
    "Deportee": 126,
    "UIFP": 22,
    "Suspect": 19,
    "UDB": 47,
    "Absconder": 106,
    "total": 709
  },
  "Jammu Kashmir & Ladakh": {
    "Arrested": 107,
    "Convicted": 145,
    "Externee": 96,
    "Deportee": 34,
    "UIFP": 194,
    "Suspect": 125,
    "UDB": 143,
    "Absconder": 72,
    "total": 916
  },
  "Jharkhand": {
    "Arrested": 113,
    "Convicted": 148,
    "Externee": 27,
    "Deportee": 194,
    "UIFP": 70,
    "Suspect": 44,
    "UDB": 58,
    "Absconder": 119,
    "total": 773
  },
  "Karnataka": {
    "Arrested": 161,
    "Convicted": 161,
    "Externee": 175,
    "Deportee": 181,
    "UIFP": 57,
    "Suspect": 65,
    "UDB": 10,
    "Absconder": 190,
    "total": 1000
  },
  "Kerala": {
    "Arrested": 100,
    "Convicted": 169,
    "Externee": 142,
    "Deportee": 62,
    "UIFP": 51,
    "Suspect": 170,
    "UDB": 106,
    "Absconder": 196,
    "total": 996
  },
  "Lakshadweep": {
    "Arrested": 147,
    "Convicted": 59,
    "Externee": 145,
    "Deportee": 192,
    "UIFP": 65,
    "Suspect": 52,
    "UDB": 78,
    "Absconder": 109,
    "total": 847
  },
  "Madhya Pradesh": {
    "Arrested": 165,
    "Convicted": 43,
    "Externee": 176,
    "Deportee": 111,
    "UIFP": 62,
    "Suspect": 15,
    "UDB": 146,
    "Absconder": 17,
    "total": 735
  },
  "Maharashtra": {
    "Arrested": 133,
    "Convicted": 45,
    "Externee": 183,
    "Deportee": 96,
    "UIFP": 173,
    "Suspect": 53,
    "UDB": 19,
    "Absconder": 77,
    "total": 779
  },
  "Manipur": {
    "Arrested": 87,
    "Convicted": 56,
    "Externee": 39,
    "Deportee": 41,
    "UIFP": 127,
    "Suspect": 135,
    "UDB": 18,
    "Absconder": 102,
    "total": 605
  },
  "Meghalaya": {
    "Arrested": 142,
    "Convicted": 63,
    "Externee": 153,
    "Deportee": 33,
    "UIFP": 115,
    "Suspect": 55,
    "UDB": 68,
    "Absconder": 149,
    "total": 778
  },
  "Mizoram": {
    "Arrested": 86,
    "Convicted": 81,
    "Externee": 116,
    "Deportee": 146,
    "UIFP": 112,
    "Suspect": 125,
    "UDB": 100,
    "Absconder": 177,
    "total": 943
  },
  "Nagaland": {
    "Arrested": 126,
    "Convicted": 67,
    "Externee": 50,
    "Deportee": 138,
    "UIFP": 40,
    "Suspect": 177,
    "UDB": 20,
    "Absconder": 88,
    "total": 706
  },
  "Odisha": {
    "Arrested": 159,
    "Convicted": 42,
    "Externee": 74,
    "Deportee": 126,
    "UIFP": 49,
    "Suspect": 95,
    "UDB": 78,
    "Absconder": 144,
    "total": 767
  },
  "Puducherry": {
    "Arrested": 166,
    "Convicted": 38,
    "Externee": 143,
    "Deportee": 96,
    "UIFP": 23,
    "Suspect": 140,
    "UDB": 126,
    "Absconder": 88,
    "total": 820
  },
  "Punjab": {
    "Arrested": 31,
    "Convicted": 104,
    "Externee": 188,
    "Deportee": 195,
    "UIFP": 122,
    "Suspect": 31,
    "UDB": 49,
    "Absconder": 153,
    "total": 873
  },
  "Rajasthan": {
    "Arrested": 58,
    "Convicted": 28,
    "Externee": 100,
    "Deportee": 50,
    "UIFP": 152,
    "Suspect": 175,
    "UDB": 23,
    "Absconder": 113,
    "total": 699
  },
  "Sikkim": {
    "Arrested": 177,
    "Convicted": 150,
    "Externee": 62,
    "Deportee": 12,
    "UIFP": 46,
    "Suspect": 86,
    "UDB": 181,
    "Absconder": 106,
    "total": 820
  },
  "Tamil Nadu": {
    "Arrested": 193,
    "Convicted": 187,
    "Externee": 153,
    "Deportee": 90,
    "UIFP": 191,
    "Suspect": 148,
    "UDB": 22,
    "Absconder": 105,
    "total": 1089
  },
  "Telangana": {
    "Arrested": 134,
    "Convicted": 114,
    "Externee": 42,
    "Deportee": 183,
    "UIFP": 155,
    "Suspect": 168,
    "UDB": 183,
    "Absconder": 37,
    "total": 1016
  },
  "Tripura": {
    "Arrested": 20,
    "Convicted": 166,
    "Externee": 11,
    "Deportee": 74,
    "UIFP": 168,
    "Suspect": 17,
    "UDB": 124,
    "Absconder": 120,
    "total": 700
  },
  "Uttar Pradesh": {
    "Arrested": 18,
    "Convicted": 45,
    "Externee": 122,
    "Deportee": 28,
    "UIFP": 155,
    "Suspect": 150,
    "UDB": 128,
    "Absconder": 156,
    "total": 802
  },
  "Uttarakhand": {
    "Arrested": 104,
    "Convicted": 191,
    "Externee": 189,
    "Deportee": 190,
    "UIFP": 95,
    "Suspect": 65,
    "UDB": 186,
    "Absconder": 82,
    "total": 1102
  },
  "West Bengal": {
    "Arrested": 129,
    "Convicted": 63,
    "Externee": 50,
    "Deportee": 164,
    "UIFP": 67,
    "Suspect": 44,
    "UDB": 127,
    "Absconder": 117,
    "total": 761
  },
  "CFPB": {
    "Arrested": 88,
    "Convicted": 119,
    "Externee": 187,
    "Deportee": 73,
    "UIFP": 110,
    "Suspect": 101,
    "UDB": 66,
    "Absconder": 39,
    "total": 783
  }
}
